README.txt
setup.py
Products/__init__.py
Products.PloneKeywordExplorer.egg-info/PKG-INFO
Products.PloneKeywordExplorer.egg-info/SOURCES.txt
Products.PloneKeywordExplorer.egg-info/dependency_links.txt
Products.PloneKeywordExplorer.egg-info/entry_points.txt
Products.PloneKeywordExplorer.egg-info/namespace_packages.txt
Products.PloneKeywordExplorer.egg-info/not-zip-safe
Products.PloneKeywordExplorer.egg-info/requires.txt
Products.PloneKeywordExplorer.egg-info/top_level.txt
Products/PloneKeywordExplorer/ABOUT
Products/PloneKeywordExplorer/CHANGES
Products/PloneKeywordExplorer/CREDITS
Products/PloneKeywordExplorer/LICENSE
Products/PloneKeywordExplorer/README.txt
Products/PloneKeywordExplorer/TODO.txt
Products/PloneKeywordExplorer/__init__.py
Products/PloneKeywordExplorer/global_symbols.py
Products/PloneKeywordExplorer/product.txt
Products/PloneKeywordExplorer/refresh.txt
Products/PloneKeywordExplorer/tool.py
Products/PloneKeywordExplorer/version.txt
Products/PloneKeywordExplorer/Extensions/Install.py
Products/PloneKeywordExplorer/doc/FAQ
Products/PloneKeywordExplorer/doc/SCREENSHOTS
Products/PloneKeywordExplorer/doc/exploring.png
Products/PloneKeywordExplorer/doc/icon.png
Products/PloneKeywordExplorer/doc/results.png
Products/PloneKeywordExplorer/i18n/plonekeywordexplorer-fr.po
Products/PloneKeywordExplorer/i18n/plonekeywordexplorer-plone-fr.po
Products/PloneKeywordExplorer/i18n/plonekeywordexplorer.pot
Products/PloneKeywordExplorer/plone3skins/README.txt
Products/PloneKeywordExplorer/plone3skins/PloneKeywordExplorer/keyword_explorer_icon.gif
Products/PloneKeywordExplorer/plone3skins/PloneKeywordExplorer/keyword_explorer_icon.gif.metadata
Products/PloneKeywordExplorer/plone3skins/PloneKeywordExplorer/searchkeywords_form.pt
Products/PloneKeywordExplorer/plone3skins/PloneKeywordExplorer/searchkeywords_form.pt.metadata
Products/PloneKeywordExplorer/skins/PloneKeywordExplorer/keyword_explorer_icon.gif
Products/PloneKeywordExplorer/skins/PloneKeywordExplorer/keyword_explorer_icon.gif.metadata
Products/PloneKeywordExplorer/skins/PloneKeywordExplorer/searchkeywords_form.pt
Products/PloneKeywordExplorer/skins/PloneKeywordExplorer/searchkeywords_form.pt.metadata
Products/PloneKeywordExplorer/website/PloneKeywordExplorer.png
Products/PloneKeywordExplorer/website/PloneKeywordExplorer_Result.png
Products/PloneKeywordExplorer/website/PloneKeywordExplorer_Search.png
