Metadata-Version: 1.0
Name: Products.PloneKeywordExplorer
Version: 0.5.0
Summary: Explore Plone content by keywords/tags
Home-page: http://svn.plone.org/svn/collective/
Author: Gilles Lenfant
Author-email: gilles.lenfant@alterway.fr
License: GPL
Keywords: plone keyword tag taxonomy navigation
Platform: UNKNOWN
Classifier: Programming Language :: Python
Classifier: Framework :: Plone
